gru_mcp_pypi/__init__.py
gru_mcp_pypi-0.1.0.dist-info/METADATA
gru_mcp_pypi-0.1.0.dist-info/WHEEL
gru_mcp_pypi-0.1.0.dist-info/entry_points.txt
gru_mcp_pypi-0.1.0.dist-info/RECORD
